.coveragerc
.testr.conf
AUTHORS
ChangeLog
HACKING.rst
LICENSE
MANIFEST.in
README.rst
babel.cfg
openstack-common.conf
requirements.txt
run_tests.sh
setup.cfg
setup.py
test-requirements.txt
tox.ini
apic_icehouse.egg-info/PKG-INFO
apic_icehouse.egg-info/SOURCES.txt
apic_icehouse.egg-info/dependency_links.txt
apic_icehouse.egg-info/entry_points.txt
apic_icehouse.egg-info/not-zip-safe
apic_icehouse.egg-info/requires.txt
apic_icehouse.egg-info/top_level.txt
apic_ml2/__init__.py
apic_ml2/neutron/__init__.py
apic_ml2/neutron/db/__init__.py
apic_ml2/neutron/db/migration/__init__.py
apic_ml2/neutron/db/migration/alembic.ini
apic_ml2/neutron/db/migration/cli.py
apic_ml2/neutron/db/migration/alembic_migrations/README
apic_ml2/neutron/db/migration/alembic_migrations/__init__.py
apic_ml2/neutron/db/migration/alembic_migrations/env.py
apic_ml2/neutron/db/migration/alembic_migrations/script.py.mako
apic_ml2/neutron/db/migration/alembic_migrations/versions/1b837a7125a9_cisco_apic_driver.py
apic_ml2/neutron/db/migration/alembic_migrations/versions/32f3915891fd_cisco_apic_driver_update.py
apic_ml2/neutron/db/migration/alembic_migrations/versions/HEAD
apic_ml2/neutron/db/migration/alembic_migrations/versions/README
apic_ml2/neutron/plugins/__init__.py
apic_ml2/neutron/plugins/ml2/__init__.py
apic_ml2/neutron/plugins/ml2/drivers/__init__.py
apic_ml2/neutron/plugins/ml2/drivers/cisco/__init__.py
apic_ml2/neutron/plugins/ml2/drivers/cisco/apic/__init__.py
apic_ml2/neutron/plugins/ml2/drivers/cisco/apic/apic_model.py
apic_ml2/neutron/plugins/ml2/drivers/cisco/apic/apic_sync.py
apic_ml2/neutron/plugins/ml2/drivers/cisco/apic/apic_topology.py
apic_ml2/neutron/plugins/ml2/drivers/cisco/apic/config.py
apic_ml2/neutron/plugins/ml2/drivers/cisco/apic/mechanism_apic.py
apic_ml2/neutron/services/__init__.py
apic_ml2/neutron/services/l3_router/__init__.py
apic_ml2/neutron/services/l3_router/l3_apic.py
apic_ml2/neutron/tests/__init__.py
apic_ml2/neutron/tests/unit/__init__.py
apic_ml2/neutron/tests/unit/ml2/__init__.py
apic_ml2/neutron/tests/unit/ml2/drivers/__init__.py
apic_ml2/neutron/tests/unit/ml2/drivers/cisco/__init__.py
apic_ml2/neutron/tests/unit/ml2/drivers/cisco/apic/__init__.py
